{
  "tabla": "data_05012015_GR2_820",
  "registros": 0,
  "campos": [
    {
      "posicion": 0,
      "campo": "VTA_PRCO",
      "tipo_sqlite": "TEXT",
      "nullable": false,
      "valor_defecto": null,
      "pk": false
    },
    {
      "posicion": 1,
      "campo": "VTA_COMP",
      "tipo_sqlite": "TEXT",
      "nullable": false,
      "valor_defecto": null,
      "pk": false
    },
    {
      "posicion": 2,
      "campo": "OPE_OPER",
      "tipo_sqlite": "TEXT",
      "nullable": false,
      "valor_defecto": null,
      "pk": false
    },
    {
      "posicion": 3,
      "campo": "CFG_ID",
      "tipo_sqlite": "INTEGER",
      "nullable": false,
      "valor_defecto": null,
      "pk": false
    },
    {
      "posicion": 4,
      "campo": "VTA_CODI",
      "tipo_sqlite": "INTEGER",
      "nullable": false,
      "valor_defecto": null,
      "pk": false
    },
    {
      "posicion": 5,
      "campo": "VTA_COD1",
      "tipo_sqlite": "TEXT",
      "nullable": false,
      "valor_defecto": null,
      "pk": false
    },
    {
      "posicion": 6,
      "campo": "VTA_DET1",
      "tipo_sqlite": "TEXT",
      "nullable": false,
      "valor_defecto": null,
      "pk": false
    },
    {
      "posicion": 7,
      "campo": "VTA_FEDE",
      "tipo_sqlite": "TEXT",
      "nullable": false,
      "valor_defecto": null,
      "pk": false
    },
    {
      "posicion": 8,
      "campo": "VTA_HODE",
      "tipo_sqlite": "TEXT",
      "nullable": false,
      "valor_defecto": null,
      "pk": false
    },
    {
      "posicion": 9,
      "campo": "VTA_FEEM",
      "tipo_sqlite": "TEXT",
      "nullable": false,
      "valor_defecto": null,
      "pk": false
    },
    {
      "posicion": 10,
      "campo": "VTA_HOEM",
      "tipo_sqlite": "TEXT",
      "nullable": false,
      "valor_defecto": null,
      "pk": false
    },
    {
      "posicion": 11,
      "campo": "VTA_FEVE",
      "tipo_sqlite": "TEXT",
      "nullable": false,
      "valor_defecto": null,
      "pk": false
    },
    {
      "posicion": 12,
      "campo": "VTA_HOVE",
      "tipo_sqlite": "TEXT",
      "nullable": false,
      "valor_defecto": null,
      "pk": false
    },
    {
      "posicion": 13,
      "campo": "VTA_PREC",
      "tipo_sqlite": "REAL",
      "nullable": false,
      "valor_defecto": null,
      "pk": false
    },
    {
      "posicion": 14,
      "campo": "VTA_SUBT",
      "tipo_sqlite": "REAL",
      "nullable": false,
      "valor_defecto": null,
      "pk": false
    },
    {
      "posicion": 15,
      "campo": "VTA_CANT",
      "tipo_sqlite": "REAL",
      "nullable": false,
      "valor_defecto": null,
      "pk": false
    },
    {
      "posicion": 16,
      "campo": "VTA_LTRA",
      "tipo_sqlite": "INTEGER",
      "nullable": false,
      "valor_defecto": null,
      "pk": false
    }
  ]
}